langchain_azure_dynamic_sessions/__init__.py
langchain_azure_dynamic_sessions/py.typed
langchain_azure_dynamic_sessions/tools/__init__.py
langchain_azure_dynamic_sessions/tools/sessions.py
gigachain_azure_dynamic_sessions-0.1.0.dist-info/LICENSE
gigachain_azure_dynamic_sessions-0.1.0.dist-info/METADATA
gigachain_azure_dynamic_sessions-0.1.0.dist-info/WHEEL
gigachain_azure_dynamic_sessions-0.1.0.dist-info/RECORD
